{
  "name": "seafile",
  "description": "Seafile is an open source file sync and share platform, focusing on reliability and performance. Seafile's built-in collaborative document SeaDoc, make it easy for collaborative writing and publishing documents.",
  "url": "https://hub.docker.com/r/seafileltd/seafile-mc",
  "longDescription": "Seafile is an open source file sync and share platform, focusing on reliability and performance. Seafile's built-in collaborative document SeaDoc, make it easy for collaborative writing and publishing documents.",
  "tags": [
    "selfhosted",
    "docker",
    "bigbear",
    "bigbearcasaos",
    "container"
  ],
  "repository": "https://github.com/bigbeartechworld",
  "image": "https://cdn.jsdelivr.net/gh/selfhst/icons/png/seafile.png",
  "supported_architectures": [
    "amd64",
    "arm64"
  ],
  "icon": "https://cdn.jsdelivr.net/gh/selfhst/icons/png/seafile.png"
}
